{
  "title": "WisprFlow vs Dragon NaturallySpeaking: I Used Both for a Month",
  "author": "Zachary Proser",
  "date": "2026-05-20",
  "description": "Dragon NaturallySpeaking is the gold standard for voice transcription. WisprFlow is the new kid on the block. I spent a month with both \u2014 here's what I found.",
  "image": "https://zackproser.b-cdn.net/images/wisprflow.webp",
  "tags": [
    "wisprflow",
    "dragon",
    "voice",
    "productivity",
    "transcription"
  ],
  "hiddenFromIndex": true
}