{
  "title": "I Am the Spark, the Bellows, and the Gate",
  "author": "Zachary Proser",
  "date": "2026-06-01",
  "description": "A stranger online said AI made him suspicious of all writing — that he now interrogates every sentence asking whether a machine wrote it. That's the wrong question. On craft in the era of AI, and why I'm still the spark, the bellows, and the gate.",
  "image": "https://zackproser.b-cdn.net/images/spark-bellows-gate-hero.webp",
  "slug": "spark-bellows-gate",
  "type": "blog",
  "keywords": ["craft", "AI writing", "creativity", "tools", "craftsmanship", "writing process"],
  "tags": ["AI", "Craft", "Writing", "Creativity", "Tools"]
}
