{
  "title": "Granola AI for Executive and Performance Coaches: Meeting Notes That Drive Client Breakthroughs",
  "author": "Zachary Proser",
  "date": "2026-03-19",
  "description": "How executive coaches and performance coaches use Granola AI to capture session insights, track client progress, and be fully present for the moments that matter most.",
  "image": "https://zackproser.b-cdn.net/images/granola-hero.webp",
  "tags": ["ai", "meetings", "coaching", "executive-coaching", "productivity"],
  "hiddenFromIndex": true
}
