{
  "title": "How to Use Voice Typing with Notion Databases in 2026: Speed Up Data Entry and Note-Taking",
  "author": "Zachary Proser",
  "date": "2026-3-5",
  "description": "Complete guide to voice typing in Notion databases for faster data entry, content management, and team collaboration workflows.",
  "image": "https://zackproser.b-cdn.net/images/wisprflow.webp",
  "slug": "/blog/voice-typing-for-notion-databases",
  "hiddenFromIndex": true,
  "keywords": [
    "how to use voice typing with Notion databases",
    "voice to text Notion 2026",
    "Notion voice dictation setup",
    "speed up Notion data entry",
    "voice typing Notion workflow",
    "Notion database voice input",
    "dictation for Notion pages",
    "voice notes in Notion",
    "Notion productivity voice tools",
    "fastest way to fill Notion database"
  ],
  "tags": [
    "Voice AI",
    "Notion",
    "Productivity",
    "Database Management"
  ]
}